disctext/__init__.py
disctext/client.py
disctext/const.py
disctext/fonts.py
disctext/syntax.py
disctext/version.py
disctext/video.py
disctext-1.0.4.dist-info/LICENSE.txt
disctext-1.0.4.dist-info/METADATA
disctext-1.0.4.dist-info/WHEEL
disctext-1.0.4.dist-info/top_level.txt
disctext-1.0.4.dist-info/RECORD
