Metadata-Version: 2.1
Name: disctext
Version: 1.0.4
Summary: A tool for creating ASCII art and sharing it on Discord.
Home-page: https://github.com/akbar-amin/disctext
Author: Akbar Amin
Author-email: akbar.amin917@gmail.com
License: MIT License
Keywords: discord,ascii,art
Platform: UNKNOWN
Requires-Dist: discord.py
Requires-Dist: opencv-python
Requires-Dist: numpy
